{
  "split": "leave-model=bert-large",
  "epochs": 50,
  "backbone": "gat",
  "constant_h": false,
  "few_shot_samples": 0,
  "filter_noisy": false,
  "metrics": [
    {
      "method": "Roofline",
      "mape": 96.05,
      "spearman": 0.843,
      "top1": 0.0
    },
    {
      "method": "Per-graph mean",
      "mape": 163.65,
      "spearman": 0.716,
      "top1": 0.0
    },
    {
      "method": "Pooled MLP",
      "mape": 53.99,
      "spearman": 0.81,
      "top1": 0.0
    },
    {
      "method": "XGBoost",
      "mape": 50.72,
      "spearman": 0.952,
      "top1": 1.0
    },
    {
      "method": "Per-kernel MLP",
      "mape": 91.94,
      "spearman": 0.793,
      "top1": 0.0
    },
    {
      "method": "GNN (gat)",
      "mape": 24.58,
      "spearman": 0.89,
      "top1": 0.0
    },
    {
      "method": "Router",
      "mape": 24.58,
      "spearman": 0.89,
      "top1": 0.0
    }
  ],
  "raw_log_path": "/results/leave_model_bert_large_gat_e50.json.log"
}